README
setup.py
cifit.egg-info/PKG-INFO
cifit.egg-info/SOURCES.txt
cifit.egg-info/dependency_links.txt
cifit.egg-info/entry_points.txt
cifit.egg-info/top_level.txt
cifitlib/__init__.py
cifitlib/appadm.py
cifitlib/classes.py
cifitlib/files.py
cifitlib/network.py
cifitlib/pkgs.py
cifitlib/procs.py
cifitlib/test_files.py
cifitlib/test_procs.py