Metadata-Version: 1.0
Name: cifit
Version: 0.3
Summary: Lightweight configuration management toolkit which you write in python
Home-page: UNKNOWN
Author: Craig Sawyer
Author-email: csawyer@yumaed.org
License: GPLv2
Keywords: config,system
Platform: UNKNOWN
